{
    "Ax": {
        "error": 1.235433622018461e-07,
        "error_type": "SEM",
        "filter_outliers_dict": {
            "filter_outliers": false,
            "iterations": 1,
            "std_devs": 2
        },
        "fit": "average",
        "value": -1.5512536522140447e-06
    },
    "H2": {
        "error": 1.2654485670994432e-07,
        "error_type": "SEM",
        "filter_outliers_dict": {
            "filter_outliers": true,
            "iterations": 1,
            "std_devs": 2
        },
        "fit": "average",
        "value": -1.4066970205113324e-06
    },
    "H4": {
        "error": 1.1226054253919069e-07,
        "error_type": "SEM",
        "filter_outliers_dict": {
            "filter_outliers": true,
            "iterations": 1,
            "std_devs": 2
        },
        "fit": "average",
        "value": -1.2668905928620687e-06
    },
    "L2": {
        "error": 1.1982558937000008e-07,
        "error_type": "SEM",
        "filter_outliers_dict": {
            "filter_outliers": true,
            "iterations": 1,
            "std_devs": 2
        },
        "fit": "average",
        "value": -1.908923072254962e-06
    },
    "L4": {
        "error": 1.107273064716533e-09,
        "error_type": "SEM",
        "filter_outliers_dict": {
            "filter_outliers": false,
            "iterations": 1,
            "std_devs": 2
        },
        "fit": "average",
        "value": 2.6666666666666666e-09
    }
}